mediasort/__init__.py
mediasort/cli.py
mediasort/file.py
mediasort/photo.py
mediasort/sort.py
mediasort/util.py
mediasort/video.py
sortmedia/__init__.py
sortmedia/cli.py
sortmedia/file.py
sortmedia/photo.py
sortmedia/sort.py
sortmedia/util.py
sortmedia/video.py
sortmedia-1.2.1.dist-info/LICENSE
sortmedia-1.2.1.dist-info/METADATA
sortmedia-1.2.1.dist-info/WHEEL
sortmedia-1.2.1.dist-info/entry_points.txt
sortmedia-1.2.1.dist-info/top_level.txt
sortmedia-1.2.1.dist-info/RECORD
