Metadata-Version: 2.1
Name: sortmedia
Version: 1.2.1
Summary: Dedupe and sort photo and video files based on the date they were created.
Home-page: https://github.com/LouisLang/sortmedia
Author: Louis Lang
Author-email: louis@lang.sh
License: UNKNOWN
Keywords: file-sorting media-manager photos videos
Platform: UNKNOWN
Requires-Dist: attrs (==19.3.0)
Requires-Dist: cffi (==1.13.2)
Requires-Dist: ffmpeg-python (==0.2.0)
Requires-Dist: filemagic (==1.6)
Requires-Dist: filetype (==1.0.5)
Requires-Dist: importlib-metadata (==1.2.0)
Requires-Dist: more-itertools (==8.0.2)
Requires-Dist: packaging (==19.2)
Requires-Dist: piexif (==1.1.3)
Requires-Dist: Pillow (==7.1.2)
Requires-Dist: pluggy (==0.13.1)
Requires-Dist: py (==1.8.0)
Requires-Dist: pycparser (==2.19)
Requires-Dist: pyheif (==0.3.2)
Requires-Dist: pyparsing (==2.4.5)
Requires-Dist: six (==1.13.0)
Requires-Dist: wcwidth (==0.1.7)
Requires-Dist: zipp (==0.6.0)
